[{
  "text": "选择正确的句子",
  "options": [
    "他把那本书看完了。",
    "他看完了把那本书。",
    "他把那本书看完。",
    "他看完把那本书了。"
  ],
  "correct": "他把那本书看完了。",
  "chars": [
    {"c": "他", "p": "tā"},
    {"c": "把", "p": "bǎ"},
    {"c": "那", "p": "nà"},
    {"c": "本", "p": "běn"},
    {"c": "书", "p": "shū"},
    {"c": "看", "p": "kàn"},
    {"c": "完", "p": "wán"},
    {"c": "了", "p": "le"},
    {"c": "。", "p": ""}
  ]
},
{
  "text": "选择正确的句子",
  "options": [
    "我被他的话感动了。",
    "我被感动了他的话。",
    "他的话把我感动了。",
    "我被他的话感动。"
  ],
  "correct": "我被他的话感动了。",
  "chars": [
    {"c": "我", "p": "wǒ"},
    {"c": "被", "p": "bèi"},
    {"c": "他", "p": "tā"},
    {"c": "的", "p": "de"},
    {"c": "话", "p": "huà"},
    {"c": "感", "p": "gǎn"},
    {"c": "动", "p": "dòng"},
    {"c": "了", "p": "le"},
    {"c": "。", "p": ""}
  ]
},
{
  "text": "选择正确的句子",
  "options": [
    "这个问题值得研究。",
    "值得这个问题研究。",
    "这个问题研究值得。",
    "研究值得这个问题。"
  ],
  "correct": "这个问题值得研究。",
  "chars": [
    {"c": "这", "p": "zhè"},
    {"c": "个", "p": "gè"},
    {"c": "问", "p": "wèn"},
    {"c": "题", "p": "tí"},
    {"c": "值", "p": "zhí"},
    {"c": "得", "p": "de"},
    {"c": "研", "p": "yán"},
    {"c": "究", "p": "jiū"},
    {"c": "。", "p": ""}
  ]
},
{
  "text": "选择正确的句子",
  "options": [
    "你明天能来参加晚会吗？",
    "你能明天来参加晚会吗？",
    "你能来参加明天晚会吗？",
    "以上都可以"
  ],
  "correct": "以上都可以",
  "chars": [
    {"c": "以", "p": "yǐ"},
    {"c": "上", "p": "shàng"},
    {"c": "都", "p": "dōu"},
    {"c": "可", "p": "kě"},
    {"c": "以", "p": "yǐ"}
  ]
},
{
  "text": "选择正确的句子",
  "options": [
    "我花了两个小时写作业。",
    "我写作业花了两个小时。",
    "我两个小时花了写作业。",
    "以上都可以"
  ],
  "correct": "以上都可以",
  "chars": [
    {"c": "以", "p": "yǐ"},
    {"c": "上", "p": "shàng"},
    {"c": "都", "p": "dōu"},
    {"c": "可", "p": "kě"},
    {"c": "以", "p": "yǐ"}
  ]
},
{
  "text": "选择正确的句子",
  "options": [
    "我每天坚持锻炼身体。",
    "我坚持每天锻炼身体。",
    "我锻炼身体每天坚持。",
    "以上都可以"
  ],
  "correct": "以上都可以",
  "chars": [
    {"c": "以", "p": "yǐ"},
    {"c": "上", "p": "shàng"},
    {"c": "都", "p": "dōu"},
    {"c": "可", "p": "kě"},
    {"c": "以", "p": "yǐ"}
  ]
},
{
  "text": "选择正确的句子",
  "options": [
    "她不仅会唱歌，还会跳舞。",
    "她不仅会唱歌，而且会跳舞。",
    "她不但会唱歌，还会跳舞。",
    "以上都可以"
  ],
  "correct": "以上都可以",
  "chars": [
    {"c": "以", "p": "yǐ"},
    {"c": "上", "p": "shàng"},
    {"c": "都", "p": "dōu"},
    {"c": "可", "p": "kě"},
    {"c": "以", "p": "yǐ"}
  ]
},
{
  "text": "选择正确的句子",
  "options": [
    "既然你已经决定了，我就不多说了。",
    "你已经决定了既然，我就不多说了。",
    "我就不多说了，既然你已经决定了。",
    "以上都可以"
  ],
  "correct": "既然你已经决定了，我就不多说了。",
  "chars": [
    {"c": "既", "p": "jì"},
    {"c": "然", "p": "rán"},
    {"c": "你", "p": "nǐ"},
    {"c": "已", "p": "yǐ"},
    {"c": "经", "p": "jīng"},
    {"c": "决", "p": "jué"},
    {"c": "定", "p": "dìng"},
    {"c": "了", "p": "le"},
    {"c": "，", "p": ""},
    {"c": "我", "p": "wǒ"},
    {"c": "就", "p": "jiù"},
    {"c": "不", "p": "bù"},
    {"c": "多", "p": "duō"},
    {"c": "说", "p": "shuō"},
    {"c": "了", "p": "le"},
    {"c": "。", "p": ""}
  ]
},
{
  "text": "选择正确的句子",
  "options": [
    "无论天气多冷，他都要去游泳。",
    "不管天气多冷，他都要去游泳。",
    "哪怕天气再冷，他也要去游泳。",
    "以上都可以"
  ],
  "correct": "以上都可以",
  "chars": [
    {"c": "以", "p": "yǐ"},
    {"c": "上", "p": "shàng"},
    {"c": "都", "p": "dōu"},
    {"c": "可", "p": "kě"},
    {"c": "以", "p": "yǐ"}
  ]
},
{
  "text": "选择正确的句子",
  "options": [
    "你既然答应了，就不能反悔。",
    "既然你答应了，就不能反悔。",
    "你不能反悔，既然答应了。",
    "以上都可以"
  ],
  "correct": "以上都可以",
  "chars": [
    {"c": "以", "p": "yǐ"},
    {"c": "上", "p": "shàng"},
    {"c": "都", "p": "dōu"},
    {"c": "可", "p": "kě"},
    {"c": "以", "p": "yǐ"}
  ]
},
{
  "text": "选择正确的句子",
  "options": [
    "即使你不说，我也知道。",
    "就算你不说，我也知道。",
    "哪怕你不说，我也知道。",
    "以上都可以"
  ],
  "correct": "以上都可以",
  "chars": [
    {"c": "以", "p": "yǐ"},
    {"c": "上", "p": "shàng"},
    {"c": "都", "p": "dōu"},
    {"c": "可", "p": "kě"},
    {"c": "以", "p": "yǐ"}
  ]
},
{
  "text": "选择正确的句子",
  "options": [
    "他宁可自己吃苦，也要帮助别人。",
    "他宁愿自己吃苦，也不让别人受苦。",
    "他宁肯自己吃亏，也要成全别人。",
    "以上都可以"
  ],
  "correct": "以上都可以",
  "chars": [
    {"c": "以", "p": "yǐ"},
    {"c": "上", "p": "shàng"},
    {"c": "都", "p": "dōu"},
    {"c": "可", "p": "kě"},
    {"c": "以", "p": "yǐ"}
  ]
},
{
  "text": "选择正确的句子",
  "options": [
    "与其坐在这里等，不如主动去找他。",
    "与其坐在这里等，还不如主动去找他。",
    "坐在这里等，不如主动去找他。",
    "以上都可以"
  ],
  "correct": "以上都可以",
  "chars": [
    {"c": "以", "p": "yǐ"},
    {"c": "上", "p": "shàng"},
    {"c": "都", "p": "dōu"},
    {"c": "可", "p": "kě"},
    {"c": "以", "p": "yǐ"}
  ]
},
{
  "text": "选择正确的句子",
  "options": [
    "他把房间打扫得干干净净。",
    "他把房间打扫干干净净。",
    "他把房间打扫得干净。",
    "他把房间打扫干干净净得。"
  ],
  "correct": "他把房间打扫得干干净净。",
  "chars": [
    {"c": "他", "p": "tā"},
    {"c": "把", "p": "bǎ"},
    {"c": "房", "p": "fáng"},
    {"c": "间", "p": "jiān"},
    {"c": "打", "p": "dǎ"},
    {"c": "扫", "p": "sǎo"},
    {"c": "得", "p": "de"},
    {"c": "干", "p": "gān"},
    {"c": "干", "p": "gān"},
    {"c": "净", "p": "jìng"},
    {"c": "净", "p": "jìng"},
    {"c": "。", "p": ""}
  ]
},
{
  "text": "选择正确的句子",
  "options": [
    "他高兴得跳了起来。",
    "他高兴地跳了起来。",
    "他高兴得跳起来。",
    "以上都可以"
  ],
  "correct": "以上都可以",
  "chars": [
    {"c": "以", "p": "yǐ"},
    {"c": "上", "p": "shàng"},
    {"c": "都", "p": "dōu"},
    {"c": "可", "p": "kě"},
    {"c": "以", "p": "yǐ"}
  ]
},
{
  "text": "选择正确的句子",
  "options": [
    "天冷得我直打哆嗦。",
    "天冷得直打哆嗦我。",
    "冷得天我直打哆嗦。",
    "我直打哆嗦天冷得。"
  ],
  "correct": "天冷得我直打哆嗦。",
  "chars": [
    {"c": "天", "p": "tiān"},
    {"c": "冷", "p": "lěng"},
    {"c": "得", "p": "de"},
    {"c": "我", "p": "wǒ"},
    {"c": "直", "p": "zhí"},
    {"c": "打", "p": "dǎ"},
    {"c": "哆", "p": "duō"},
    {"c": "嗦", "p": "suo"},
    {"c": "。", "p": ""}
  ]
},
{
  "text": "选择正确的句子",
  "options": [
    "他跑得比我快多了。",
    "他跑得比我快得多。",
    "他比我跑得快多了。",
    "以上都可以"
  ],
  "correct": "以上都可以",
  "chars": [
    {"c": "以", "p": "yǐ"},
    {"c": "上", "p": "shàng"},
    {"c": "都", "p": "dōu"},
    {"c": "可", "p": "kě"},
    {"c": "以", "p": "yǐ"}
  ]
},
{
  "text": "选择正确的句子",
  "options": [
    "他的汉语说得越来越好了。",
    "他汉语说得越来越好了。",
    "他汉语越来越好说了。",
    "以上都可以"
  ],
  "correct": "他的汉语说得越来越好了。",
  "chars": [
    {"c": "他", "p": "tā"},
    {"c": "的", "p": "de"},
    {"c": "汉", "p": "hàn"},
    {"c": "语", "p": "yǔ"},
    {"c": "说", "p": "shuō"},
    {"c": "得", "p": "de"},
    {"c": "越", "p": "yuè"},
    {"c": "来", "p": "lái"},
    {"c": "越", "p": "yuè"},
    {"c": "好", "p": "hǎo"},
    {"c": "了", "p": "le"},
    {"c": "。", "p": ""}
  ]
},
{
  "text": "选择正确的句子",
  "options": [
    "你越解释，我越糊涂。",
    "你越解释我越糊涂。",
    "我越糊涂你越解释。",
    "以上都可以"
  ],
  "correct": "你越解释，我越糊涂。",
  "chars": [
    {"c": "你", "p": "nǐ"},
    {"c": "越", "p": "yuè"},
    {"c": "解", "p": "jiě"},
    {"c": "释", "p": "shì"},
    {"c": "，", "p": ""},
    {"c": "我", "p": "wǒ"},
    {"c": "越", "p": "yuè"},
    {"c": "糊", "p": "hú"},
    {"c": "涂", "p": "tú"},
    {"c": "。", "p": ""}
  ]
},
{
  "text": "选择正确的句子",
  "options": [
    "他一边走路，一边听音乐。",
    "他一边听音乐，一边走路。",
    "他走路一边，听音乐一边。",
    "以上都可以"
  ],
  "correct": "他一边走路，一边听音乐。",
  "chars": [
    {"c": "他", "p": "tā"},
    {"c": "一", "p": "yī"},
    {"c": "边", "p": "biān"},
    {"c": "走", "p": "zǒu"},
    {"c": "路", "p": "lù"},
    {"c": "，", "p": ""},
    {"c": "一", "p": "yī"},
    {"c": "边", "p": "biān"},
    {"c": "听", "p": "tīng"},
    {"c": "音", "p": "yīn"},
    {"c": "乐", "p": "yuè"},
    {"c": "。", "p": ""}
  ]
},
{
  "text": "选择正确的句子",
  "options": [
    "他先吃了饭，然后去看电影。",
    "他吃了饭，然后去看电影。",
    "他吃完饭，然后去看电影。",
    "以上都可以"
  ],
  "correct": "以上都可以",
  "chars": [
    {"c": "以", "p": "yǐ"},
    {"c": "上", "p": "shàng"},
    {"c": "都", "p": "dōu"},
    {"c": "可", "p": "kě"},
    {"c": "以", "p": "yǐ"}
  ]
},
{
  "text": "选择正确的句子",
  "options": [
    "我一进门，就看见他了。",
    "我一进门就看见他了。",
    "我看见他一进门就。",
    "以上都可以"
  ],
  "correct": "我一进门，就看见他了。",
  "chars": [
    {"c": "我", "p": "wǒ"},
    {"c": "一", "p": "yī"},
    {"c": "进", "p": "jìn"},
    {"c": "门", "p": "mén"},
    {"c": "，", "p": ""},
    {"c": "就", "p": "jiù"},
    {"c": "看", "p": "kàn"},
    {"c": "见", "p": "jiàn"},
    {"c": "他", "p": "tā"},
    {"c": "了", "p": "le"},
    {"c": "。", "p": ""}
  ]
},
{
  "text": "选择正确的句子",
  "options": [
    "他刚走，你就来了。",
    "他刚走你就来了。",
    "你来了他刚走。",
    "以上都可以"
  ],
  "correct": "他刚走，你就来了。",
  "chars": [
    {"c": "他", "p": "tā"},
    {"c": "刚", "p": "gāng"},
    {"c": "走", "p": "zǒu"},
    {"c": "，", "p": ""},
    {"c": "你", "p": "nǐ"},
    {"c": "就", "p": "jiù"},
    {"c": "来", "p": "lái"},
    {"c": "了", "p": "le"},
    {"c": "。", "p": ""}
  ]
},
{
  "text": "选择正确的句子",
  "options": [
    "他不但没来，而且连电话也没打。",
    "他不但没来，连电话也没打。",
    "他不但没来，电话也没打。",
    "以上都可以"
  ],
  "correct": "以上都可以",
  "chars": [
    {"c": "以", "p": "yǐ"},
    {"c": "上", "p": "shàng"},
    {"c": "都", "p": "dōu"},
    {"c": "可", "p": "kě"},
    {"c": "以", "p": "yǐ"}
  ]
},
{
  "text": "选择正确的句子",
  "options": [
    "他不但会说英语，还会说法语。",
    "他不仅会说英语，还会说法语。",
    "他不但会说英语，而且会说法语。",
    "以上都可以"
  ],
  "correct": "以上都可以",
  "chars": [
    {"c": "以", "p": "yǐ"},
    {"c": "上", "p": "shàng"},
    {"c": "都", "p": "dōu"},
    {"c": "可", "p": "kě"},
    {"c": "以", "p": "yǐ"}
  ]
},
{
  "text": "选择正确的句子",
  "options": [
    "他把窗户擦得干干净净。",
    "他把窗户擦干干净净。",
    "他把窗户擦得干净。",
    "他把窗户擦干干净净得。"
  ],
  "correct": "他把窗户擦得干干净净。",
  "chars": [
    {"c": "他", "p": "tā"},
    {"c": "把", "p": "bǎ"},
    {"c": "窗", "p": "chuāng"},
    {"c": "户", "p": "hu"},
    {"c": "擦", "p": "cā"},
    {"c": "得", "p": "de"},
    {"c": "干", "p": "gān"},
    {"c": "干", "p": "gān"},
    {"c": "净", "p": "jìng"},
    {"c": "净", "p": "jìng"},
    {"c": "。", "p": ""}
  ]
},
{
  "text": "选择正确的句子",
  "options": [
    "他把衣服洗得干干净净。",
    "他把衣服洗干干净净。",
    "他把衣服洗得干净。",
    "他把衣服洗干干净净得。"
  ],
  "correct": "他把衣服洗得干干净净。",
  "chars": [
    {"c": "他", "p": "tā"},
    {"c": "把", "p": "bǎ"},
    {"c": "衣", "p": "yī"},
    {"c": "服", "p": "fu"},
    {"c": "洗", "p": "xǐ"},
    {"c": "得", "p": "de"},
    {"c": "干", "p": "gān"},
    {"c": "干", "p": "gān"},
    {"c": "净", "p": "jìng"},
    {"c": "净", "p": "jìng"},
    {"c": "。", "p": ""}
  ]
},
{
  "text": "选择正确的句子",
  "options": [
    "他把作业做完了。",
    "他做完了把作业。",
    "他把作业做完。",
    "他做完把作业了。"
  ],
  "correct": "他把作业做完了。",
  "chars": [
    {"c": "他", "p": "tā"},
    {"c": "把", "p": "bǎ"},
    {"c": "作", "p": "zuò"},
    {"c": "业", "p": "yè"},
    {"c": "做", "p": "zuò"},
    {"c": "完", "p": "wán"},
    {"c": "了", "p": "le"},
    {"c": "。", "p": ""}
  ]
},
{
  "text": "选择正确的句子",
  "options": [
    "我把钥匙忘在家里了。",
    "我忘带钥匙了。",
    "钥匙忘在家里了。",
    "以上都可以"
  ],
  "correct": "以上都可以",
  "chars": [
    {"c": "以", "p": "yǐ"},
    {"c": "上", "p": "shàng"},
    {"c": "都", "p": "dōu"},
    {"c": "可", "p": "kě"},
    {"c": "以", "p": "yǐ"}
  ]
},
{
  "text": "选择正确的句子",
  "options": [
    "他把钱包丢了。",
    "他丢了钱包。",
    "钱包被他丢了。",
    "以上都可以"
  ],
  "correct": "以上都可以",
  "chars": [
    {"c": "以", "p": "yǐ"},
    {"c": "上", "p": "shàng"},
    {"c": "都", "p": "dōu"},
    {"c": "可", "p": "kě"},
    {"c": "以", "p": "yǐ"}
  ]
},
{
  "text": "选择正确的句子",
  "options": [
    "你赶快去吧，不然就迟到了。",
    "你赶快去吧，要不就迟到了。",
    "你赶快去吧，否则就迟到了。",
    "以上都可以"
  ],
  "correct": "以上都可以",
  "chars": [
    {"c": "以", "p": "yǐ"},
    {"c": "上", "p": "shàng"},
    {"c": "都", "p": "dōu"},
    {"c": "可", "p": "kě"},
    {"c": "以", "p": "yǐ"}
  ]
},
{
  "text": "选择正确的句子",
  "options": [
    "他居然敢骗我！",
    "他竟然敢骗我！",
    "他居然敢骗我！",
    "以上都可以"
  ],
  "correct": "以上都可以",
  "chars": [
    {"c": "以", "p": "yǐ"},
    {"c": "上", "p": "shàng"},
    {"c": "都", "p": "dōu"},
    {"c": "可", "p": "kě"},
    {"c": "以", "p": "yǐ"}
  ]
},
{
  "text": "选择正确的句子",
  "options": [
    "他做作业做到很晚。",
    "他做作业做得很晚。",
    "他作业做得很晚。",
    "以上都可以"
  ],
  "correct": "以上都可以",
  "chars": [
    {"c": "以", "p": "yǐ"},
    {"c": "上", "p": "shàng"},
    {"c": "都", "p": "dōu"},
    {"c": "可", "p": "kě"},
    {"c": "以", "p": "yǐ"}
  ]
},
{
  "text": "选择正确的句子",
  "options": [
    "他唱歌唱得很好听。",
    "他唱歌得很好听。",
    "他唱歌好听得很。",
    "他唱歌唱得好听。"
  ],
  "correct": "他唱歌唱得很好听。",
  "chars": [
    {"c": "他", "p": "tā"},
    {"c": "唱", "p": "chàng"},
    {"c": "歌", "p": "gē"},
    {"c": "唱", "p": "chàng"},
    {"c": "得", "p": "de"},
    {"c": "很", "p": "hěn"},
    {"c": "好", "p": "hǎo"},
    {"c": "听", "p": "tīng"},
    {"c": "。", "p": ""}
  ]
},
{
  "text": "选择正确的句子",
  "options": [
    "他跳舞跳得很好。",
    "他跳舞得很好。",
    "他跳舞好得很。",
    "他跳舞跳得好。"
  ],
  "correct": "他跳舞跳得很好。",
  "chars": [
    {"c": "他", "p": "tā"},
    {"c": "跳", "p": "tiào"},
    {"c": "舞", "p": "wǔ"},
    {"c": "跳", "p": "tiào"},
    {"c": "得", "p": "de"},
    {"c": "很", "p": "hěn"},
    {"c": "好", "p": "hǎo"},
    {"c": "。", "p": ""}
  ]
},
{
  "text": "选择正确的句子",
  "options": [
    "他开车开得很快。",
    "他开车得很快。",
    "他开车快得很。",
    "他开得快车。"
  ],
  "correct": "他开车开得很快。",
  "chars": [
    {"c": "他", "p": "tā"},
    {"c": "开", "p": "kāi"},
    {"c": "车", "p": "chē"},
    {"c": "开", "p": "kāi"},
    {"c": "得", "p": "de"},
    {"c": "很", "p": "hěn"},
    {"c": "快", "p": "kuài"},
    {"c": "。", "p": ""}
  ]
},
{
  "text": "选择正确的句子",
  "options": [
    "他说话说得太快了。",
    "他说话得太快了。",
    "他说话快得太了。",
    "他说得快话了。"
  ],
  "correct": "他说话说得太快了。",
  "chars": [
    {"c": "他", "p": "tā"},
    {"c": "说", "p": "shuō"},
    {"c": "话", "p": "huà"},
    {"c": "说", "p": "shuō"},
    {"c": "得", "p": "de"},
    {"c": "太", "p": "tài"},
    {"c": "快", "p": "kuài"},
    {"c": "了", "p": "le"},
    {"c": "。", "p": ""}
  ]
},
{
  "text": "选择正确的句子",
  "options": [
    "你为什么不告诉我？",
    "你怎么不告诉我？",
    "你为啥不告诉我？",
    "以上都可以"
  ],
  "correct": "以上都可以",
  "chars": [
    {"c": "以", "p": "yǐ"},
    {"c": "上", "p": "shàng"},
    {"c": "都", "p": "dōu"},
    {"c": "可", "p": "kě"},
    {"c": "以", "p": "yǐ"}
  ]
},
{
  "text": "选择正确的句子",
  "options": [
    "你什么时候来的？",
    "你什么时候来？",
    "你来什么时候的？",
    "以上都可以"
  ],
  "correct": "你什么时候来的？",
  "chars": [
    {"c": "你", "p": "nǐ"},
    {"c": "什", "p": "shén"},
    {"c": "么", "p": "me"},
    {"c": "时", "p": "shí"},
    {"c": "候", "p": "hou"},
    {"c": "来", "p": "lái"},
    {"c": "的", "p": "de"},
    {"c": "？", "p": ""}
  ]
},
{
  "text": "选择正确的句子",
  "options": [
    "你吃了饭没有？",
    "你吃饭了没有？",
    "你吃了饭没？",
    "以上都可以"
  ],
  "correct": "以上都可以",
  "chars": [
    {"c": "以", "p": "yǐ"},
    {"c": "上", "p": "shàng"},
    {"c": "都", "p": "dōu"},
    {"c": "可", "p": "kě"},
    {"c": "以", "p": "yǐ"}
  ]
},
{
  "text": "选择正确的句子",
  "options": [
    "你能帮我一个忙吗？",
    "你能帮我一下吗？",
    "你能帮我个忙吗？",
    "以上都可以"
  ],
  "correct": "以上都可以",
  "chars": [
    {"c": "以", "p": "yǐ"},
    {"c": "上", "p": "shàng"},
    {"c": "都", "p": "dōu"},
    {"c": "可", "p": "kě"},
    {"c": "以", "p": "yǐ"}
  ]
},
{
  "text": "选择正确的句子",
  "options": [
    "这个菜很好吃。",
    "这个菜好吃得很。",
    "这个菜很好吃。",
    "以上都可以"
  ],
  "correct": "以上都可以",
  "chars": [
    {"c": "以", "p": "yǐ"},
    {"c": "上", "p": "shàng"},
    {"c": "都", "p": "dōu"},
    {"c": "可", "p": "kě"},
    {"c": "以", "p": "yǐ"}
  ]
},
{
  "text": "选择正确的句子",
  "options": [
    "这个电影我看过。",
    "我看过这个电影。",
    "这个电影我看过了。",
    "以上都可以"
  ],
  "correct": "以上都可以",
  "chars": [
    {"c": "以", "p": "yǐ"},
    {"c": "上", "p": "shàng"},
    {"c": "都", "p": "dōu"},
    {"c": "可", "p": "kě"},
    {"c": "以", "p": "yǐ"}
  ]
},
{
  "text": "选择正确的句子",
  "options": [
    "这本书我看过。",
    "我看过这本书。",
    "这本书我看过了。",
    "以上都可以"
  ],
  "correct": "以上都可以",
  "chars": [
    {"c": "以", "p": "yǐ"},
    {"c": "上", "p": "shàng"},
    {"c": "都", "p": "dōu"},
    {"c": "可", "p": "kě"},
    {"c": "以", "p": "yǐ"}
  ]
},
{
  "text": "选择正确的句子",
  "options": [
    "我跟他借了一本书。",
    "我借了他一本书。",
    "我向他借了一本书。",
    "以上都可以"
  ],
  "correct": "以上都可以",
  "chars": [
    {"c": "以", "p": "yǐ"},
    {"c": "上", "p": "shàng"},
    {"c": "都", "p": "dōu"},
    {"c": "可", "p": "kě"},
    {"c": "以", "p": "yǐ"}
  ]
},
{
  "text": "选择正确的句子",
  "options": [
    "他把礼物送给我了。",
    "他送给我礼物了。",
    "他送了礼物给我。",
    "以上都可以"
  ],
  "correct": "以上都可以",
  "chars": [
    {"c": "以", "p": "yǐ"},
    {"c": "上", "p": "shàng"},
    {"c": "都", "p": "dōu"},
    {"c": "可", "p": "kě"},
    {"c": "以", "p": "yǐ"}
  ]
},
{
  "text": "选择正确的句子",
  "options": [
    "你跟我一起去吗？",
    "你和我一起去吗？",
    "你同我一起去吗？",
    "以上都可以"
  ],
  "correct": "以上都可以",
  "chars": [
    {"c": "以", "p": "yǐ"},
    {"c": "上", "p": "shàng"},
    {"c": "都", "p": "dōu"},
    {"c": "可", "p": "kě"},
    {"c": "以", "p": "yǐ"}
  ]
},
{
  "text": "选择正确的句子",
  "options": [
    "我比他大三岁。",
    "我比他大三岁。",
    "我比他大岁三。",
    "我比他三岁大。"
  ],
  "correct": "我比他大三岁。",
  "chars": [
    {"c": "我", "p": "wǒ"},
    {"c": "比", "p": "bǐ"},
    {"c": "他", "p": "tā"},
    {"c": "大", "p": "dà"},
    {"c": "三", "p": "sān"},
    {"c": "岁", "p": "suì"},
    {"c": "。", "p": ""}
  ]
},
{
  "text": "选择正确的句子",
  "options": [
    "我比他高。",
    "我高比他。",
    "我比他很高。",
    "我比他更高。"
  ],
  "correct": "我比他高。",
  "chars": [
    {"c": "我", "p": "wǒ"},
    {"c": "比", "p": "bǐ"},
    {"c": "他", "p": "tā"},
    {"c": "高", "p": "gāo"},
    {"c": "。", "p": ""}
  ]
},
{
  "text": "选择正确的句子",
  "options": [
    "你多大了？",
    "你几岁了？",
    "你多大年纪了？",
    "以上都可以"
  ],
  "correct": "以上都可以",
  "chars": [
    {"c": "以", "p": "yǐ"},
    {"c": "上", "p": "shàng"},
    {"c": "都", "p": "dōu"},
    {"c": "可", "p": "kě"},
    {"c": "以", "p": "yǐ"}
  ]
}]